pynacci/__init__.py
pynacci/fibonacci.py
fibonacci_checker-1.0.dist-info/METADATA
fibonacci_checker-1.0.dist-info/WHEEL
fibonacci_checker-1.0.dist-info/top_level.txt
fibonacci_checker-1.0.dist-info/RECORD
