Metadata-Version: 2.1
Name: fibonacci_checker
Version: 1.0
Summary: A library to check if a number is in the Fibonacci sequence
Home-page: https://www.linkedin.com/in/pabblo2000/
Author: Pablo Álvaro
Author-email: palvaroh2000@example.com
Classifier: Programming Language :: Python :: 3
Classifier: License :: OSI Approved :: MIT License
Classifier: Operating System :: OS Independent
